{
    "version": "https://jsonfeed.org/version/1",
    "title": "碎念随风 • All posts by \"实时数仓\" category",
    "description": "人海未见之时，我亦独行在这城市。 料峭，春醒，酷暑，骤雨，寒意四起，大雁南飞，而后，大雪，寒风， 斗转星移，人间寒暑。",
    "home_page_url": "http://example.com",
    "items": [
        {
            "id": "http://example.com/2024/03/07/BaiduSyncdisk/%E5%AE%9E%E6%97%B6%E6%95%B0%E4%BB%93%E6%90%AD%E5%BB%BA/",
            "url": "http://example.com/2024/03/07/BaiduSyncdisk/%E5%AE%9E%E6%97%B6%E6%95%B0%E4%BB%93%E6%90%AD%E5%BB%BA/",
            "title": "实时数仓搭建",
            "date_published": "2024-03-07T05:52:09.000Z",
            "content_html": "",
            "tags": []
        }
    ]
}